droneops/__init__.py
droneops/droneops.py
droneops/mission_planner.py
droneops/q_ground_control.py
tests/__init__.py
tests/test_droneops.py
tests/test_mission_planner.py
tests/test_q_ground_control.py
droneops-0.1.0.dist-info/METADATA
droneops-0.1.0.dist-info/WHEEL
droneops-0.1.0.dist-info/entry_points.txt
droneops-0.1.0.dist-info/top_level.txt
droneops-0.1.0.dist-info/RECORD
