Metadata-Version: 2.2
Name: droneops
Version: 0.1.0
Summary: Advanced drone control and mission planning library
Home-page: https://github.com/droneops/droneops
Author: Rui Afonso Martins
Author-email: martins.ruiafonso@gmail.com
Project-URL: Bug Tracker, https://github.com/droneops/droneops/issues
Project-URL: Documentation, https://droneops.readthedocs.io/
Project-URL: Source, https://github.com/rafonsomartins/droneops
Classifier: Programming Language :: Python :: 3
Classifier: Programming Language :: Python :: 3.7
Classifier: Programming Language :: Python :: 3.8
Classifier: Programming Language :: Python :: 3.9
Classifier: Programming Language :: Python :: 3.10
Classifier: License :: OSI Approved :: MIT License
Classifier: Operating System :: OS Independent
Classifier: Development Status :: 4 - Beta
Classifier: Intended Audience :: Developers
Classifier: Intended Audience :: Science/Research
Classifier: Topic :: Scientific/Engineering
Classifier: Topic :: Scientific/Engineering :: GIS
Classifier: Topic :: Software Development :: Libraries :: Python Modules
Requires-Python: >=3.7
Requires-Dist: numpy>=1.19.0
Requires-Dist: dronekit>=2.9.2
Requires-Dist: pymavlink>=2.4.0
Requires-Dist: shapely>=1.7.0
Provides-Extra: kml
Requires-Dist: fastkml>=0.11; extra == "kml"
Provides-Extra: dev
Requires-Dist: pytest>=6.0.0; extra == "dev"
Requires-Dist: pytest-cov>=2.0.0; extra == "dev"
Requires-Dist: black>=21.0.0; extra == "dev"
Requires-Dist: flake8>=3.9.0; extra == "dev"
Requires-Dist: sphinx>=4.0.0; extra == "dev"
Requires-Dist: sphinx-rtd-theme>=0.5.0; extra == "dev"
Dynamic: author
Dynamic: author-email
Dynamic: classifier
Dynamic: description
Dynamic: description-content-type
Dynamic: home-page
Dynamic: project-url
Dynamic: provides-extra
Dynamic: requires-dist
Dynamic: requires-python
Dynamic: summary
